arm64_tester/__init__.py
arm64_tester/main.py
arm64_tester/test.py
arm64_tester/tester.py
arm64_tester/exception/__init__.py
arm64_tester/exception/compile_error.py
arm64_tester/exception/runtime_error.py
arm64_tester/exception/tool_file_error.py
arm64_tester/parameters/__init__.py
arm64_tester/parameters/array_parameter.py
arm64_tester/parameters/numeric_parameter.py
arm64_tester/parameters/parameter.py
arm64_tester/parameters/string_parameter.py
arm64_tester/subroutines/__init__.py
arm64_tester/subroutines/array_subroutine.py
arm64_tester/subroutines/mixed_subroutine.py
arm64_tester/subroutines/numeric_subroutine.py
arm64_tester/subroutines/subroutine.py
arm64_tester/subroutines/void_subroutine.py
arm64_tester/util/__init__.py
arm64_tester/util/type_casting.py
arm64_tester-1.2.4.dist-info/LICENSE
arm64_tester-1.2.4.dist-info/METADATA
arm64_tester-1.2.4.dist-info/WHEEL
arm64_tester-1.2.4.dist-info/top_level.txt
arm64_tester-1.2.4.dist-info/RECORD
