Metadata-Version: 2.1
Name: arm64-tester
Version: 1.2.4
Author: Luis Tavares
Classifier: Programming Language :: Python :: 3
Classifier: Programming Language :: Python :: 3.6
Classifier: Programming Language :: Python :: 3.7
Classifier: Programming Language :: Python :: 3.8
Classifier: License :: OSI Approved :: MIT License
Classifier: Operating System :: OS Independent
Requires-Python: >=3.6
License-File: LICENSE
Requires-Dist: PyYAML (==5.4)
Requires-Dist: Unidecode (==1.2.0)
